graphUtilscd_harshita/__init__.py
graphUtilscd_harshita/algorithms.py
graphUtilscd_harshita/utils.py
graphutilscd_harshita-1.0.0.dist-info/LICENSE
graphutilscd_harshita-1.0.0.dist-info/WHEEL
graphutilscd_harshita-1.0.0.dist-info/METADATA
graphutilscd_harshita-1.0.0.dist-info/RECORD
