Metadata-Version: 2.3
Name: graphUtilscd_harshita
Version: 1.0.0
Summary: graphUtils - A Python package providing graph algorithms such as Dijkstra, Bellman-Ford, Floyd-Warshall, and Topological Sorting.
Author-email: Harshita <harshita19062004@gmail.com>
Classifier: License :: OSI Approved :: MIT License
